{
  "text_block_list": [
    {
      "name": "Bamboo Memory",
      "text": "Oguri, I challenge you!! \nYou and me, on the racecourse!"
    },
    {
      "name": "Oguri Cap",
      "text": "Sure thing. But…"
    },
    {
      "name": "Oguri Cap",
      "text": "Can it wait till after I finish this pork bun? \nAfter all…"
    },
    {
      "name": "Oguri Cap",
      "text": "Pork buns should be eaten \nwhen they're still hot!"
    },
    {
      "name": "Bamboo Memory",
      "text": "What are you saying?! Why…"
    },
    {
      "name": "Bamboo Memory",
      "text": "Of course you should finish that first! \nNow hurry up and eat it!!"
    },
    {
      "name": "Oguri Cap",
      "text": "Heh… You got it!"
    }
  ],
  "no_wrap": true
}